nr/__init__.py
nr/fs/__init__.py
nr/fs/_atomic.py
nr/fs/_mtime_consistent_file.py
nr/fs/_path.py
nr/fs/_tempfile.py
nr.fs-1.6.3.dist-info/LICENSE.txt
nr.fs-1.6.3.dist-info/METADATA
nr.fs-1.6.3.dist-info/WHEEL
nr.fs-1.6.3.dist-info/top_level.txt
nr.fs-1.6.3.dist-info/zip-safe
nr.fs-1.6.3.dist-info/RECORD
