Metadata-Version: 2.1
Name: nr.fs
Version: 1.6.3
Summary: Filesystem and path manipulation tools.
Home-page: https://git.niklasrosenstein.com/NiklasRosenstein/nr
Author: Niklas Rosenstein
Author-email: rosensteinniklas@gmail.com
License: MIT
Platform: UNKNOWN
